{
  "Routes": [
    // Employer API
    {
      "DownstreamPathTemplate": "/api/company/{email}",
      "DownstreamScheme": "https",
      "DownstreamHostAndPorts": [
        {
          "Host": "localhost",
          "Port": 7284
        }
      ],
      "UpstreamPathTemplate": "/api/company/{email}",
      "UpstreamhttpMethod": [ "Get" ]
    },
    {
      "DownstreamPathTemplate": "/api/company/getProfileByName/{name}",
      "DownstreamScheme": "https",
      "DownstreamHostAndPorts": [
        {
          "Host": "localhost",
          "Port": 7284
        }
      ],
      "UpstreamPathTemplate": "/api/company/getProfileByName/{name}",
      "UpstreamhttpMethod": [ "Get" ]
    },
    {
      "DownstreamPathTemplate": "/api/company/addDetails",
      "DownstreamScheme": "https",
      "DownstreamHostAndPorts": [
        {
          "Host": "localhost",
          "Port": 7284
        }
      ],
      "UpstreamPathTemplate": "/api/company/addDetails",
      "UpstreamhttpMethod": [ "Post" ],
      "AuthenticationOptions": {
        "AuthenticationProviderKey": "Bearer"
      }
    },
    {
      "DownstreamPathTemplate": "/api/company/updateDetails/{email}",
      "DownstreamScheme": "https",
      "DownstreamHostAndPorts": [
        {
          "Host": "localhost",
          "Port": 7284
        }
      ],
      "UpstreamPathTemplate": "/api/company/updateDetails/{email}",
      "UpstreamhttpMethod": [ "Put" ],
      "AuthenticationOptions": {
        "AuthenticationProviderKey": "Bearer"
      }
    },
    {
      "DownstreamPathTemplate": "/api/vacancy/getAllVacancies",
      "DownstreamScheme": "https",
      "DownstreamHostAndPorts": [
        {
          "Host": "localhost",
          "Port": 7284
        }
      ],
      "UpstreamPathTemplate": "/api/vacancy/getAllVacancies",
      "UpstreamhttpMethod": [ "Get" ]
    },
    {
      "DownstreamPathTemplate": "/api/vacancy/getVacancyById/{id}",
      "DownstreamScheme": "https",
      "DownstreamHostAndPorts": [
        {
          "Host": "localhost",
          "Port": 7284
        }
      ],
      "UpstreamPathTemplate": "/api/vacancy/getVacancyById/{id}",
      "UpstreamhttpMethod": [ "Get" ]
    },
    {
      "DownstreamPathTemplate": "/api/vacancy/getByCompany/{email}",
      "DownstreamScheme": "https",
      "DownstreamHostAndPorts": [
        {
          "Host": "localhost",
          "Port": 7284
        }
      ],
      "UpstreamPathTemplate": "/api/vacancy/getByCompany/{email}",
      "UpstreamhttpMethod": [ "Get" ]
    },
    {
      "DownstreamPathTemplate": "/api/vacancy/addVacancy",
      "DownstreamScheme": "https",
      "DownstreamHostAndPorts": [
        {
          "Host": "localhost",
          "Port": 7284
        }
      ],
      "UpstreamPathTemplate": "/api/vacancy/addVacancy",
      "UpstreamhttpMethod": [ "Post" ],
      "AuthenticationOptions": {
        "AuthenticationProviderKey": "Bearer"
      }
    },
    {
      "DownstreamPathTemplate": "/api/vacancy/updateVacancy/{id}",
      "DownstreamScheme": "https",
      "DownstreamHostAndPorts": [
        {
          "Host": "localhost",
          "Port": 7284
        }
      ],
      "UpstreamPathTemplate": "/api/vacancy/updateVacancy/{id}",
      "UpstreamhttpMethod": [ "Put" ],
      "AuthenticationOptions": {
        "AuthenticationProviderKey": "Bearer"
      }
    },
    {
      "DownstreamPathTemplate": "/api/vacancy/deleteVacancy/{id}",
      "DownstreamScheme": "https",
      "DownstreamHostAndPorts": [
        {
          "Host": "localhost",
          "Port": 7284
        }
      ],
      "UpstreamPathTemplate": "/api/vacancy/deleteVacancy/{id}",
      "UpstreamhttpMethod": [ "Delete" ],
      "AuthenticationOptions": {
        "AuthenticationProviderKey": "Bearer"
      }
    },
    {
      "DownstreamPathTemplate": "/api/application/getAllByUser/{id}",
      "DownstreamScheme": "https",
      "DownstreamHostAndPorts": [
        {
          "Host": "localhost",
          "Port": 7284
        }
      ],
      "UpstreamPathTemplate": "/api/application/getAllByUser/{id}",
      "UpstreamhttpMethod": [ "Get" ],
      "AuthenticationOptions": {
        "AuthenticationProviderKey": "Bearer"
      }
    },
    {
      "DownstreamPathTemplate": "/api/application/getAllByVacancy/{id}",
      "DownstreamScheme": "https",
      "DownstreamHostAndPorts": [
        {
          "Host": "localhost",
          "Port": 7284
        }
      ],
      "UpstreamPathTemplate": "/api/application/getAllByVacancy/{id}",
      "UpstreamhttpMethod": [ "Get" ],
      "AuthenticationOptions": {
        "AuthenticationProviderKey": "Bearer"
      }
    },
    {
      "DownstreamPathTemplate": "/api/application/createApplication",
      "DownstreamScheme": "https",
      "DownstreamHostAndPorts": [
        {
          "Host": "localhost",
          "Port": 7284
        }
      ],
      "UpstreamPathTemplate": "/api/application/createApplication",
      "UpstreamhttpMethod": [ "Post" ],
      "AuthenticationOptions": {
        "AuthenticationProviderKey": "Bearer"
      }
    },

    // JobSeeker API
    {
      "DownstreamPathTemplate": "/api/jobSeeker/getByEmail/{email}",
      "DownstreamScheme": "https",
      "DownstreamHostAndPorts": [
        {
          "Host": "localhost",
          "Port": 7246
        }
      ],
      "UpstreamPathTemplate": "/api/jobSeeker/getByEmail/{email}",
      "UpstreamhttpMethod": [ "Get" ],
      "AuthenticationOptions": {
        "AuthenticationProviderKey": "Bearer"
      }
    },
    {
      "DownstreamPathTemplate": "/api/jobSeeker/getByUserId/{userId}",
      "DownstreamScheme": "https",
      "DownstreamHostAndPorts": [
        {
          "Host": "localhost",
          "Port": 7246
        }
      ],
      "UpstreamPathTemplate": "/api/jobSeeker/getByUserId/{userId}",
      "UpstreamhttpMethod": [ "Get" ],
      "AuthenticationOptions": {
        "AuthenticationProviderKey": "Bearer"
      }
    },
    {
      "DownstreamPathTemplate": "/api/jobSeeker/addProfile",
      "DownstreamScheme": "https",
      "DownstreamHostAndPorts": [
        {
          "Host": "localhost",
          "Port": 7246
        }
      ],
      "UpstreamPathTemplate": "/api/jobSeeker/addProfile",
      "UpstreamhttpMethod": [ "Post" ],
      "AuthenticationOptions": {
        "AuthenticationProviderKey": "Bearer"
      }
    },
    {
      "DownstreamPathTemplate": "/api/jobSeeker/uploadResume",
      "DownstreamScheme": "https",
      "DownstreamHostAndPorts": [
        {
          "Host": "localhost",
          "Port": 7246
        }
      ],
      "UpstreamPathTemplate": "/api/jobSeeker/uploadResume",
      "UpstreamhttpMethod": [ "Post" ],
      "AuthenticationOptions": {
        "AuthenticationProviderKey": "Bearer"
      }
    },
    {
      "DownstreamPathTemplate": "/api/jobSeeker/updateProfile/{email}",
      "DownstreamScheme": "https",
      "DownstreamHostAndPorts": [
        {
          "Host": "localhost",
          "Port": 7246
        }
      ],
      "UpstreamPathTemplate": "/api/jobSeeker/updateProfile/{email}",
      "UpstreamhttpMethod": [ "Put" ],
      "AuthenticationOptions": {
        "AuthenticationProviderKey": "Bearer"
      }
    },
    {
      "DownstreamPathTemplate": "/api/experience/getAllExperiencesByUserId/{userId}",
      "DownstreamScheme": "https",
      "DownstreamHostAndPorts": [
        {
          "Host": "localhost",
          "Port": 7246
        }
      ],
      "UpstreamPathTemplate": "/api/experience/getAllExperiencesByUserId/{userId}",
      "UpstreamhttpMethod": [ "Get" ],
      "AuthenticationOptions": {
        "AuthenticationProviderKey": "Bearer"
      }
    },
    {
      "DownstreamPathTemplate": "/api/experience/getExperienceById/{id}",
      "DownstreamScheme": "https",
      "DownstreamHostAndPorts": [
        {
          "Host": "localhost",
          "Port": 7246
        }
      ],
      "UpstreamPathTemplate": "/api/experience/getExperienceById/{id}",
      "UpstreamhttpMethod": [ "Get" ],
      "AuthenticationOptions": {
        "AuthenticationProviderKey": "Bearer"
      }
    },
    {
      "DownstreamPathTemplate": "/api/experience/addExperience",
      "DownstreamScheme": "https",
      "DownstreamHostAndPorts": [
        {
          "Host": "localhost",
          "Port": 7246
        }
      ],
      "UpstreamPathTemplate": "/api/experience/addExperience",
      "UpstreamhttpMethod": [ "Post" ],
      "AuthenticationOptions": {
        "AuthenticationProviderKey": "Bearer"
      }
    },
    {
      "DownstreamPathTemplate": "/api/experience/updateExperience/{id}",
      "DownstreamScheme": "https",
      "DownstreamHostAndPorts": [
        {
          "Host": "localhost",
          "Port": 7246
        }
      ],
      "UpstreamPathTemplate": "/api/experience/updateExperience/{id}",
      "UpstreamhttpMethod": [ "Put" ],
      "AuthenticationOptions": {
        "AuthenticationProviderKey": "Bearer"
      }
    },
    {
      "DownstreamPathTemplate": "/api/experience/deleteExperience/{id}",
      "DownstreamScheme": "https",
      "DownstreamHostAndPorts": [
        {
          "Host": "localhost",
          "Port": 7246
        }
      ],
      "UpstreamPathTemplate": "/api/experience/deleteExperience/{id}",
      "UpstreamhttpMethod": [ "Delete" ],
      "AuthenticationOptions": {
        "AuthenticationProviderKey": "Bearer"
      }
    },
    {
      "DownstreamPathTemplate": "/api/qualification/GetAllQualificationsByUserId/{id}",
      "DownstreamScheme": "https",
      "DownstreamHostAndPorts": [
        {
          "Host": "localhost",
          "Port": 7246
        }
      ],
      "UpstreamPathTemplate": "/api/qualification/GetAllQualificationsByUserId/{id}",
      "UpstreamhttpMethod": [ "Get" ],
      "AuthenticationOptions": {
        "AuthenticationProviderKey": "Bearer"
      }
    },
    {
      "DownstreamPathTemplate": "/api/qualification/GetQualificationById/{id}",
      "DownstreamScheme": "https",
      "DownstreamHostAndPorts": [
        {
          "Host": "localhost",
          "Port": 7246
        }
      ],
      "UpstreamPathTemplate": "/api/qualification/GetQualificationById/{id}",
      "UpstreamhttpMethod": [ "Get" ],
      "AuthenticationOptions": {
        "AuthenticationProviderKey": "Bearer"
      }
    },
    {
      "DownstreamPathTemplate": "/api/qualification/addQualification",
      "DownstreamScheme": "https",
      "DownstreamHostAndPorts": [
        {
          "Host": "localhost",
          "Port": 7246
        }
      ],
      "UpstreamPathTemplate": "/api/qualification/addQualification",
      "UpstreamhttpMethod": [ "Post" ],
      "AuthenticationOptions": {
        "AuthenticationProviderKey": "Bearer"
      }
    },
    {
      "DownstreamPathTemplate": "/api/qualification/updateQualification/{id}",
      "DownstreamScheme": "https",
      "DownstreamHostAndPorts": [
        {
          "Host": "localhost",
          "Port": 7246
        }
      ],
      "UpstreamPathTemplate": "/api/qualification/updateQualification/{id}",
      "UpstreamhttpMethod": [ "Put" ],
      "AuthenticationOptions": {
        "AuthenticationProviderKey": "Bearer"
      }
    },
    {
      "DownstreamPathTemplate": "/api/qualification/deleteQualification/{id}",
      "DownstreamScheme": "https",
      "DownstreamHostAndPorts": [
        {
          "Host": "localhost",
          "Port": 7246
        }
      ],
      "UpstreamPathTemplate": "/api/qualification/deleteQualification/{id}",
      "UpstreamhttpMethod": [ "Delete" ],
      "AuthenticationOptions": {
        "AuthenticationProviderKey": "Bearer"
      }
    }
  ],
  "GlobalConfiguration": {
    "BaseUrl": "https://localhost:7777"
  }
}
